benchmark_imports/__init__.py
benchmark_imports/__main__.py
benchmark_imports/_cli.py
benchmark_imports/_colors.py
benchmark_imports/_imports.py
benchmark_imports/_stack.py
benchmark_imports/_tracker.py
benchmark_imports-1.0.0.dist-info/LICENSE
benchmark_imports-1.0.0.dist-info/WHEEL
benchmark_imports-1.0.0.dist-info/METADATA
benchmark_imports-1.0.0.dist-info/RECORD
