Metadata-Version: 2.1
Name: benchmark-imports
Version: 1.0.0
Summary: A CLI tool to record how much time it takes to import each dependency.
Keywords: import,benchmark,profile,profiler,time,performance,cli
Author-email: Gram <gram@orsinium.dev>
Requires-Python: >=3.7
Classifier: Development Status :: 5 - Production/Stable
Classifier: Intended Audience :: Developers
Classifier: License :: OSI Approved :: MIT License
Classifier: Programming Language :: Python
Classifier: Topic :: Software Development
Classifier: Topic :: Software Development :: Quality Assurance
Requires-Dist: pytest ; extra == "test"
Project-URL: Source, https://github.com/orsinium-labs/benchmark-imports
Provides-Extra: test
